avrogen/__init__.py
avrogen/__main__.py
avrogen/avrojson.py
avrogen/core_writer.py
avrogen/dict_wrapper.py
avrogen/logical.py
avrogen/namespace.py
avrogen/protocol.py
avrogen/protocol_writer.py
avrogen/py.typed
avrogen/schema.py
avrogen/tabbed_writer.py
avro_gen3-0.7.15.dist-info/LICENSE
avro_gen3-0.7.15.dist-info/METADATA
avro_gen3-0.7.15.dist-info/WHEEL
avro_gen3-0.7.15.dist-info/top_level.txt
avro_gen3-0.7.15.dist-info/RECORD
