Metadata-Version: 2.1
Name: avro-gen3
Version: 0.7.15
Summary: Avro record class and specific record reader generator
Home-page: https://github.com/acryldata/avro_gen
Author: Harshal Sheth
Author-email: hsheth2@gmail.com
License: License :: OSI Approved :: Apache Software License
Keywords: avro class generator
Classifier: Development Status :: 4 - Beta
Classifier: Intended Audience :: Developers
Classifier: License :: OSI Approved :: Apache Software License
Classifier: Programming Language :: Python :: 3.5
Classifier: Programming Language :: Python :: 3.6
Classifier: Programming Language :: Python :: 3.7
Classifier: Programming Language :: Python :: 3.8
License-File: LICENSE
Requires-Dist: avro >=1.10
Requires-Dist: six
